profilist/__init__.py
profilist/profiler.py
profilist/py.typed
profilist/timer.py
profilist-7.0.0.dist-info/METADATA
profilist-7.0.0.dist-info/WHEEL
profilist-7.0.0.dist-info/RECORD
