Metadata-Version: 2.4
Name: profilist
Version: 7.0.0
Summary: A collection of code for profilist.
Project-URL: Homepage, https://github.com/gao-hongnan/profilist
Project-URL: Issues, https://github.com/gao-hongnan/profilist/issues
Author-email: GAO Hongnan <hongnangao@gmail.com>
Classifier: License :: OSI Approved :: Apache Software License
Classifier: Operating System :: OS Independent
Classifier: Programming Language :: Python :: 3
Classifier: Programming Language :: Python :: 3.12
Classifier: Programming Language :: Python :: 3.13
Requires-Python: >=3.12
Requires-Dist: psutil>=7.1.3
Requires-Dist: pydantic>=2.11.7
Requires-Dist: types-psutil>=7.0.0.20251115
Provides-Extra: memory
Requires-Dist: cffi>=1.15.0; extra == 'memory'
Requires-Dist: scalene>=1.5.0; extra == 'memory'
